git_pnp-1.5.0.dist-info/licenses/LICENSE
pnp/__init__.py
pnp/__main__.py
pnp/_constants.py
pnp/cli.py
pnp/github.py
pnp/gitutils.py
pnp/help_menu.py
pnp/py.typed
pnp/resolver.py
pnp/utils.py
git_pnp-1.5.0.dist-info/METADATA
git_pnp-1.5.0.dist-info/WHEEL
git_pnp-1.5.0.dist-info/entry_points.txt
git_pnp-1.5.0.dist-info/top_level.txt
git_pnp-1.5.0.dist-info/RECORD
