Metadata-Version: 2.4
Name: git-pnp
Version: 1.5.0
Summary: A robust Python CLI tool to manage Git workflows with intelligent commit, push, tagging, changelog generation, GitHub releases, hook execution, and error handling.
Author: Caleb M. Sibanda
Author-email: darkian.dev@gmail.com
License: MIT
Project-URL: Homepage, https://github.com/2kDarki/pnp
Project-URL: Documentation, https://github.com/2kDarki/pnp#readme
Project-URL: Repository, https://github.com/2kDarki/pnp
Project-URL: Issues, https://github.com/2kDarki/pnp/issues
Keywords: git,automation,cli,release,devops,python
Classifier: Development Status :: 5 - Production/Stable
Classifier: Environment :: Console
Classifier: Intended Audience :: Developers
Classifier: License :: OSI Approved :: MIT License
Classifier: Programming Language :: Python :: 3
Classifier: Programming Language :: Python :: 3 :: Only
Classifier: Programming Language :: Python :: 3.10
Classifier: Programming Language :: Python :: 3.11
Classifier: Programming Language :: Python :: 3.12
Classifier: Operating System :: OS Independent
Classifier: Topic :: Software Development :: Version Control :: Git
Requires-Python: >=3.10
License-File: LICENSE
Requires-Dist: requests>=2.32.5
Requires-Dist: tuikit>=0.2.5
Provides-Extra: dev
Requires-Dist: drace; extra == "dev"
Dynamic: author
Dynamic: author-email
Dynamic: license-file
